anonupload/__init__.py
anonupload/cli.py
anonupload/config.py
anonupload/main.py
anonupload-1.4.4.dist-info/licenses/LICENSE
anonupload-1.4.4.dist-info/METADATA
anonupload-1.4.4.dist-info/WHEEL
anonupload-1.4.4.dist-info/entry_points.txt
anonupload-1.4.4.dist-info/top_level.txt
anonupload-1.4.4.dist-info/RECORD
