Metadata-Version: 2.4
Name: anonupload
Version: 1.4.4
Summary: upload and download to anonfiles server
Home-page: https://github.com/jakbin/anonupload
Author: Jak Bin
Author-email: jakbin4747@gmail.com
Project-URL: Bug Tracker, https://github.com/jakbin/anonupload/issues
Keywords: anonfile,anonfile-api,anonfile-cli,anonymous,upload
Classifier: Programming Language :: Python :: 3.6
Classifier: License :: OSI Approved :: MIT License
Classifier: Natural Language :: English
Classifier: Operating System :: OS Independent
Requires-Python: >=3
License-File: LICENSE
Requires-Dist: tqdm
Requires-Dist: requests
Requires-Dist: requests-toolbelt
Requires-Dist: appdirs
Dynamic: author
Dynamic: author-email
Dynamic: classifier
Dynamic: description
Dynamic: description-content-type
Dynamic: home-page
Dynamic: keywords
Dynamic: license-file
Dynamic: project-url
Dynamic: requires-dist
Dynamic: requires-python
Dynamic: summary
